wexample_filestate_python-0.0.58.dist-info/METADATA
wexample_filestate_python-0.0.58.dist-info/WHEEL
wexample_filestate_python-0.0.58.dist-info/entry_points.txt
wexample_filestate_python/__init__.py
wexample_filestate_python/__pycache__/__init__.py
wexample_filestate_python/common/__init__.py
wexample_filestate_python/common/__pycache__/__init__.py
wexample_filestate_python/common/pipy_gateway.py
wexample_filestate_python/config_option/__init__.py
wexample_filestate_python/config_option/__pycache__/__init__.py
wexample_filestate_python/config_option/mixin/__init__.py
wexample_filestate_python/config_option/mixin/__pycache__/__init__.py
wexample_filestate_python/config_option/mixin/with_stdout_wrapping_mixin.py
wexample_filestate_python/config_value/__init__.py
wexample_filestate_python/config_value/__pycache__/__init__.py
wexample_filestate_python/config_value/python_config_value.py
wexample_filestate_python/const/__init__.py
wexample_filestate_python/const/__pycache__/__init__.py
wexample_filestate_python/const/name_pattern.py
wexample_filestate_python/const/path.py
wexample_filestate_python/const/python_file.py
wexample_filestate_python/event/__init__.py
wexample_filestate_python/event/src/__init__.py
wexample_filestate_python/event/src/wexample_event/__init__.py
wexample_filestate_python/file/__init__.py
wexample_filestate_python/file/__pycache__/__init__.py
wexample_filestate_python/file/python_file.py
wexample_filestate_python/helpers/__init__.py
wexample_filestate_python/helpers/__pycache__/__init__.py
wexample_filestate_python/helpers/package.py
wexample_filestate_python/helpers/python/__init__.py
wexample_filestate_python/helpers/toml.py
wexample_filestate_python/option/__init__.py
wexample_filestate_python/option/__pycache__/__init__.py
wexample_filestate_python/option/python/__init__.py
wexample_filestate_python/option/python/abstract_python_file_content_option.py
wexample_filestate_python/option/python/add_future_annotations_option.py
wexample_filestate_python/option/python/add_return_types_option.py
wexample_filestate_python/option/python/class_name_matches_file_name_option.py
wexample_filestate_python-0.0.58.dist-info/RECORD
