Metadata-Version: 2.1
Name: wexample-filestate-python
Version: 0.0.58
Summary: Helpers for Python.
Author-Email: weeger <contact@wexample.com>
License: MIT
Classifier: Programming Language :: Python :: 3
Classifier: License :: OSI Approved :: MIT License
Classifier: Operating System :: OS Independent
Project-URL: homepage, https://github.com/wexample/python-filestate-python
Requires-Python: >=3.10
Requires-Dist: attrs>=23.1.0
Requires-Dist: autoflake
Requires-Dist: black
Requires-Dist: cattrs>=23.1.0
Requires-Dist: flynt
Requires-Dist: isort
Requires-Dist: libcst
Requires-Dist: packaging
Requires-Dist: pyupgrade
Requires-Dist: tomli
Requires-Dist: wexample-api==0.0.83
Requires-Dist: wexample-filestate==0.0.74
Provides-Extra: dev
Requires-Dist: pytest; extra == "dev"
Requires-Dist: pytest-cov; extra == "dev"
